{
  "noc": "22212",
  "title": "NOC 22212 – Drafting Technologists and Technicians | GTR Immigration",
  "slug": "noc-22212-drafting-technologists-and-technicians-gtr-immigration",
  "description": "Drafting Technologists and Technicians are in strong demand across Canada, fueled by post-pandemic construction growth, infrastructure renewal, advanced manufacturing, and large-scale utility and resource projects. Classified under NOC 22212 (TEER 2), this occupation aligns well with:",
  "classification": {
    "category": "2 – Natural and applied sciences",
    "teer": "2 – College diploma or apprenticeship normally required",
    "major_group": "222 – Applied sciences (except engineering)",
    "sub_major_group": "N/A",
    "minor_group": "2221 – Architecture, drafting, surveying & geomatics"
  },
  "common_job_titles": [
    "Drafting technologist",
    "Drafting technician",
    "Architectural draftsperson",
    "BIM technologist",
    "CAD/CADD technician",
    "Engineering design & drafting technologist",
    "Structural steel drafter-detailer",
    "Mechanical draftsperson",
    "Electrical or electronic draftsperson",
    "Steel detailer – drafting",
    "Drafting office supervisor"
  ],
  "duties": [
    "Professionals in this role typically:",
    "Drafting Technologists",
    "Develop engineering drawings from technical concepts",
    "Create BIM models for buildings & infrastructure",
    "Operate CAD workstations",
    "Prepare documentation packages & drawing sets",
    "Verify designs against specifications",
    "Produce technical reports & tender documents",
    "Estimate construction costs & materials",
    "Supervise drafting teams",
    "Drafting Technicians",
    "Produce plans, diagrams & layouts from sketches",
    "Operate drafting software or manual stations",
    "Support senior technologists and engineers"
  ],
  "employment_requirements": [
    "Applicants usually require:",
    "Completion of secondary school",
    "Two- to three-year college diploma in engineering design & drafting technology (technologists)",
    "One- to two-year drafting diploma, apprenticeship, or equivalent experience (technicians)",
    "Optional trade certification in Ontario",
    "Provincial technologist-association certification (employer-preferred)",
    "Around two years of supervised work experience for certification"
  ],
  "salary_prospects": [
    {
      "region": "Canada (Average)",
      "low": "20.00",
      "median": "28.70",
      "high": "41.44"
    },
    {
      "region": "Alberta",
      "low": "25.00",
      "median": "36.00",
      "high": "46.00"
    },
    {
      "region": "British Columbia",
      "low": "21.00",
      "median": "30.00",
      "high": "42.50"
    },
    {
      "region": "Manitoba",
      "low": "19.49",
      "median": "26.88",
      "high": "42.56"
    },
    {
      "region": "New Brunswick",
      "low": "19.00",
      "median": "27.96",
      "high": "32.50"
    },
    {
      "region": "Newfoundland and Labrador",
      "low": "18.27",
      "median": "28.00",
      "high": "37.59"
    },
    {
      "region": "Nova Scotia",
      "low": "18.27",
      "median": "28.00",
      "high": "35.00"
    },
    {
      "region": "Ontario",
      "low": "20.00",
      "median": "30.00",
      "high": "38.00"
    },
    {
      "region": "Prince Edward Island",
      "low": "19.14",
      "median": "25.48",
      "high": "41.57"
    },
    {
      "region": "Quebec",
      "low": "19.00",
      "median": "25.00",
      "high": "35.90"
    },
    {
      "region": "Saskatchewan",
      "low": "23.00",
      "median": "31.00",
      "high": "40.87"
    }
  ],
  "job_outlook": [
    "Canada projects:",
    "12,500 new openings",
    "21,600 job seekers",
    "This competitive outlook favours candidates with:",
    "Advanced BIM & CAD expertise",
    "Infrastructure-project exposure",
    "Structural-steel detailing experience",
    "Utility or manufacturing-sector backgrounds",
    "Provincial technologist certification"
  ],
  "labour_market_demand": [],
  "benefits": [],
  "pathways": [
    "Professionals benefit from:",
    "Skilled-occupation PR eligibility",
    "Provincial nomination opportunities",
    "Stable multi-sector employment",
    "Competitive wages & benefits",
    "Public healthcare coverage",
    "Long-term infrastructure-sector careers",
    "Advancement into BIM, design-management, or supervisory roles"
  ],
  "additional_information": [
    "Labour-Market Demand",
    "Canadian employers continue to recruit drafting professionals for:",
    "Construction & consulting firmsManufacturing plantsUtilities & energy companiesMining & resource operationsTransportation & infrastructure agenciesFederal, provincial & municipal governments",
    "Annual salaries typically range between $38,500–$79,800 CAD, depending on province, certification, and technical specialization."
  ]
}