{
  "noc": "41220",
  "title": "NOC 41220 – Secondary School Teachers | GTR Immigration",
  "slug": "noc-41220-secondary-school-teachers-gtr-immigration",
  "description": "Secondary School Teachers under NOC 41220 are licensed education professionals responsible for teaching academic, vocational, and specialized subjects to students at the high school level across Canada. Classified as TEER 1 (Professional Occupation), this role is central to Canada’s public and private education systems. These educators prepare students for post-secondary education, skilled trades, and entry into the workforce, while supporting their academic, social, and personal development.",
  "classification": {
    "category": "N/A",
    "teer": "Classification LevelDetailsBroad Occupation Category4 – Occupations in education, law, and social, community, and government servicesTEER1 – Occupations usually require a university degreeMajor Group41 – Professional occupations in law, education, social, community and government servicesSub-Major Group412 – Professional occupations in education servicesMinor Group4122 – Secondary, elementary and kindergarten school teachersNOC Code41220",
    "major_group": "N/A",
    "sub_major_group": "N/A",
    "minor_group": "N/A"
  },
  "common_job_titles": [
    "Adult education teacher – secondary school",
    "Biology teacher – secondary school",
    "Commerce teacher – secondary school",
    "English as a Second Language (ESL) high school teacher",
    "English teacher – secondary school",
    "French as a Second Language teacher – secondary school",
    "History teacher – secondary school",
    "Librarian-teacher – high school",
    "Remedial teacher – secondary school",
    "Secondary school department head",
    "Secondary school teacher",
    "Special education teacher – secondary school",
    "Supply high school teacher",
    "Trades instructor – secondary school",
    "Vocational teacher – secondary school"
  ],
  "duties": [
    "Secondary School Teachers perform some or all of the following duties:",
    "Prepare and deliver subject material according to approved curriculum",
    "Teach through lectures, discussions, audio-visual presentations, and lab/shop sessions",
    "Assign and correct homework",
    "Prepare, administer, and grade tests",
    "Evaluate student progress and determine learning needs",
    "Communicate progress with parents and school administrators",
    "Develop and implement remedial programs",
    "Participate in staff meetings and professional development workshops",
    "Teach online or distance education courses",
    "Advise students on academic and career pathways",
    "Supervise student teachers"
  ],
  "employment_requirements": [
    "Bachelor’s degree in Education (B.Ed.)",
    "Often preceded by a Bachelor’s degree in Arts or Sciences (for academic subjects)",
    "Vocational teachers require specialized training or trade experience",
    "In Quebec, trade instructors require apprenticeship completion and trade certification",
    "Several years of teaching experience for department head roles",
    "Additional training for:Special educationESL or FSL (French as a Second Language)",
    "Special education",
    "ESL or FSL (French as a Second Language)",
    "Provincial teaching certificate required",
    "Membership in provincial teachers’ association may be required",
    "Foreign-trained teachers must obtain credential assessment and provincial certification before practicing."
  ],
  "salary_prospects": [
    {
      "region": "Canada",
      "low": "28.57",
      "median": "43.96",
      "high": "55.38"
    },
    {
      "region": "Alberta",
      "low": "28.85",
      "median": "45.67",
      "high": "55.49"
    },
    {
      "region": "British Columbia",
      "low": "27.67",
      "median": "40.87",
      "high": "52.20"
    },
    {
      "region": "Manitoba",
      "low": "26.44",
      "median": "42.31",
      "high": "52.31"
    },
    {
      "region": "New Brunswick",
      "low": "25.64",
      "median": "25.64",
      "high": "42.79"
    },
    {
      "region": "Newfoundland and Labrador",
      "low": "26.44",
      "median": "44.23",
      "high": "60.92"
    },
    {
      "region": "Northwest Territories",
      "low": "30.58",
      "median": "50.13",
      "high": "64.42"
    },
    {
      "region": "Nova Scotia",
      "low": "27.88",
      "median": "41.35",
      "high": "52.53"
    },
    {
      "region": "Nunavut",
      "low": "27.51",
      "median": "55.43",
      "high": "69.18"
    },
    {
      "region": "Ontario",
      "low": "31.15",
      "median": "47.74",
      "high": "60.00"
    },
    {
      "region": "Prince Edward Island",
      "low": "24.04",
      "median": "38.46",
      "high": "45.64"
    },
    {
      "region": "Quebec",
      "low": "27.47",
      "median": "40.26",
      "high": "51.08"
    },
    {
      "region": "Saskatchewan",
      "low": "30.77",
      "median": "43.27",
      "high": "52.60"
    },
    {
      "region": "Yukon Territory",
      "low": "31.50",
      "median": "47.63",
      "high": "51.70"
    },
    "Annual Salary Range",
    "Secondary School Teachers typically earn between:",
    "$38,500 – $111,400 per year, depending on province, years of experience, and subject specialization.",
    "Teachers in Northern territories often receive additional allowances and benefits."
  ],
  "job_outlook": [
    "The employment outlook for Secondary School Teachers is stable and positive due to:",
    "Retirement of senior educators",
    "Population growth in urban centers",
    "Expansion of vocational education programs",
    "Increasing need for bilingual and special education teachers",
    "Competition can vary by province and subject area."
  ],
  "labour_market_demand": [
    "Secondary School Teachers are employed in:",
    "Public secondary schools",
    "Private high schools",
    "Specialized or alternative education programs",
    "Online and distance education platforms",
    "Job Market Projections (2022–2031)",
    "52,100 new job openings",
    "47,800 new job seekers",
    "Demand is driven by:",
    "Population growth",
    "Teacher retirements",
    "Increased enrollment",
    "Expansion of special education and ESL programs",
    "Growth in vocational and trade education streams",
    "Opportunities are available nationwide, particularly in Ontario, Alberta, British Columbia, Saskatchewan, and Northern territories.",
    "Why Immigrate Under NOC 41220?",
    "This occupation offers:",
    "TEER 1 skilled classification",
    "Strong public sector job stability",
    "Competitive provincial salary scales",
    "Public healthcare and pension benefits",
    "High demand in rural and northern regions",
    "Clear pathway to department head and school leadership roles",
    "Teachers specializing in STEM subjects, French immersion, ESL, and special education are especially in demand."
  ],
  "benefits": [],
  "pathways": [
    "Secondary School Teachers qualify under high-skilled TEER 1 immigration categories and may apply through:",
    "Express Entry (Federal Skilled Worker Program)",
    "Provincial Nominee Programs (PNPs)",
    "Employer-supported work permits",
    "Education-sector provincial streams",
    "Foreign educators must complete provincial certification after immigration."
  ],
  "additional_information": []
}